{
  "entityType" : "ENTITY_GROUP",
  "entity" : {
    "additionalInfo" : {
      "description" : "Autogenerated Customer Administrators group with all permissions."
    },
    "configuration" : {
      "columns" : [ {
        "type" : "ENTITY_FIELD",
        "key" : "created_time",
        "sortOrder" : "DESC"
      }, {
        "type" : "ENTITY_FIELD",
        "key" : "first_name",
        "sortOrder" : "NONE"
      }, {
        "type" : "ENTITY_FIELD",
        "key" : "last_name",
        "sortOrder" : "NONE"
      }, {
        "type" : "ENTITY_FIELD",
        "key" : "email",
        "sortOrder" : "NONE"
      } ],
      "settings" : { },
      "actions" : { }
    },
    "edgeGroupAll" : false,
    "externalId" : null,
    "groupAll" : false,
    "id" : {
      "entityType" : "ENTITY_GROUP",
      "id" : "0afbb9a0-ee35-11ed-8899-9ba30be05e76"
    },
    "name" : "Customer Administrators",
    "ownerId" : {
      "entityType" : "CUSTOMER",
      "id" : "0ae12cc0-ee35-11ed-8899-9ba30be05e76"
    },
    "type" : "USER"
  },
  "relations" : [ ],
  "attributes" : {
    "SERVER_SCOPE" : [ ]
  },
  "groupEntities" : true,
  "permissions" : [ {
    "entityGroupId" : null,
    "entityGroupType" : null,
    "roleId" : {
      "entityType" : "ROLE",
      "id" : "0afcf220-ee35-11ed-8899-9ba30be05e76"
    },
    "tenantId" : {
      "entityType" : "TENANT",
      "id" : "d587b990-ee11-11ed-97ca-e57c88951dd5"
    },
    "userGroupId" : {
      "entityType" : "ENTITY_GROUP",
      "id" : "0afbb9a0-ee35-11ed-8899-9ba30be05e76"
    },
    "createdTime" : 1683614710359,
    "id" : {
      "entityType" : "GROUP_PERMISSION",
      "id" : "0b002670-ee35-11ed-8899-9ba30be05e76"
    },
    "name" : "GENERIC_[0afbb9a0-ee35-11ed-8899-9ba30be05e76]_[0afcf220-ee35-11ed-8899-9ba30be05e76]",
    "public" : false
  } ]
}